affinity_model/.gitattributes
affinity_model/README.md
affinity_model/__init__.py
affinity_model/base.py
affinity_model/v1.py
affinity_model/v2.py
affinity_model/tests/__init__.py
affinity_model/tests/test_v1.py
affinity_model/tests/test_v2.py
affinity_model/tests/__snapshots__/test_v1/test_note.json
affinity_model/v2/__init__.py
affinity_model/v2/interactions.py
affinity_model-0.0.2.dist-info/METADATA
affinity_model-0.0.2.dist-info/WHEEL
affinity_model-0.0.2.dist-info/licenses/LICENSE
affinity_model-0.0.2.dist-info/RECORD
