Metadata-Version: 2.4
Name: affinity-model
Version: 0.0.2
Summary: A data model for the Affinity CRM API
Author-email: Planet A GmbH <dev@planet-a.com>
License-Expression: MIT
License-File: LICENSE
Classifier: Operating System :: OS Independent
Classifier: Programming Language :: Python :: 3.12
Requires-Python: >=3.12
